{
  "id": "05",
  "slug": "模型評估",
  "title": "模型評估與驗證方法",
  "filename": "05-模型評估.json",
  "html": "<h1>05 — 模型評估與驗證方法</h1>\n\n<p>模型評估是 ML 工程中最關鍵的環節。選錯指標或驗證方式會導致模型上線後效能大幅下降。本章全面講解分類/迴歸指標、交叉驗證方法、以及常見陷阱。</p>\n\n<h2>一、分類指標</h2>\n<h3>混淆矩陣（Confusion Matrix）</h3>\n<table>\n<thead><tr><th></th><th>預測正</th><th>預測負</th></tr></thead>\n<tbody>\n<tr><td><strong>實際正</strong></td><td>TP（真正）</td><td>FN（偽負）</td></tr>\n<tr><td><strong>實際負</strong></td><td>FP（偽正）</td><td>TN（真負）</td></tr>\n</tbody>\n</table>\n\n<h3>核心指標</h3>\n<table>\n<thead><tr><th>指標</th><th>公式</th><th>意義</th><th>適用場景</th></tr></thead>\n<tbody>\n<tr><td>Accuracy</td><td>(TP+TN)/(TP+TN+FP+FN)</td><td>整體正確率</td><td>類別平衡時</td></tr>\n<tr><td><strong>Precision</strong></td><td>TP/(TP+FP)</td><td>預測為正的正確率</td><td>重視誤報成本（垃圾郵件）</td></tr>\n<tr><td><strong>Recall</strong></td><td>TP/(TP+FN)</td><td>實際正例的被找到比率</td><td>重視漏報成本（癌症篩檢）</td></tr>\n<tr><td><strong>F1 Score</strong></td><td>2PR/(P+R)</td><td>P 和 R 的調和平均</td><td>需兼顧兩者</td></tr>\n<tr><td>AUC-ROC</td><td>ROC 曲線下面積</td><td>不受閾值影響的整體效能</td><td>比較不同模型</td></tr>\n</tbody>\n</table>\n<p><strong>F1 計算範例</strong>：P=0.8, R=0.6 → F1 = 2×0.8×0.6/(0.8+0.6) = 0.96/1.4 ≈ <strong>0.686</strong></p>\n\n<h2>二、迴歸指標</h2>\n<table>\n<thead><tr><th>指標</th><th>公式</th><th>特點</th></tr></thead>\n<tbody>\n<tr><td>MSE</td><td>(1/n)Σ(y-ŷ)²</td><td>放大大誤差的影響</td></tr>\n<tr><td>RMSE</td><td>√MSE</td><td>與原始單位相同</td></tr>\n<tr><td>MAE</td><td>(1/n)Σ|y-ŷ|</td><td>對離群值穩健</td></tr>\n<tr><td><strong>R²</strong></td><td>1 - SS<sub>res</sub>/SS<sub>tot</sub></td><td>可解釋的變異比例（0.85 = 85% 變異可被解釋）</td></tr>\n</tbody>\n</table>\n\n<h2>三、交叉驗證方法</h2>\n<table>\n<thead><tr><th>方法</th><th>做法</th><th>優點</th><th>缺點</th><th>適用場景</th></tr></thead>\n<tbody>\n<tr><td>Hold-out</td><td>切一次（如 80/20）</td><td>簡單快速</td><td>結果不穩定</td><td>資料量大</td></tr>\n<tr><td><strong>K-Fold CV</strong></td><td>分 K 份輪流驗證</td><td>所有資料都被驗證</td><td>計算量較大</td><td>通用</td></tr>\n<tr><td>Stratified K-Fold</td><td>K-Fold + 保持類別比例</td><td>避免類別偏斜</td><td>同上</td><td><strong>類別不平衡</strong></td></tr>\n<tr><td>LOOCV</td><td>每次留 1 筆</td><td>資料利用率最高</td><td>計算量極大</td><td>小樣本</td></tr>\n<tr><td>Time Series CV</td><td>滑動視窗</td><td>尊重時序</td><td>訓練資料逐漸增大</td><td>時間序列</td></tr>\n</tbody>\n</table>\n\n<h2>四、Nested Cross-Validation</h2>\n<p><strong>問題</strong>：若在同一層 CV 上同時調超參數和評估效能 → 資料洩漏 → 過度樂觀</p>\n<p><strong>解法</strong>：Nested CV = 外層（評估泛化效能）+ 內層（搜尋最佳超參數）</p>\n\n<h2>五、常見陷阱</h2>\n<ul>\n<li><strong>類別不平衡時用 Accuracy</strong>：99% 負例時，全猜負 Accuracy=99% 但毫無意義</li>\n<li><strong>時序資料用隨機分割</strong>：會造成未來資訊洩漏，應用時序 CV</li>\n<li><strong>在測試集上調參</strong>：等於作弊，應分離 validation set</li>\n<li><strong>只看單一指標</strong>：需綜合看 P/R/F1 + 混淆矩陣 + ROC</li>\n</ul>\n\n<h2>Key Points 速記</h2>\n<ul>\n<li>F1 = 2PR/(P+R)，調和平均兼顧 Precision 和 Recall</li>\n<li>R² = 0.85 表示 85% 變異可被模型解釋</li>\n<li>類別不平衡 → Stratified K-Fold + F1/AUC（非 Accuracy）</li>\n<li>超參數調整 + 評估需用 Nested CV 避免過度樂觀</li>\n<li>時序資料禁止隨機分割，需用 Time Series CV</li>\n</ul>"
}